gt4sd_molformer/__init__.py
gt4sd_molformer/finetune/__init__.py
gt4sd_molformer/finetune/bert_vocab.txt
gt4sd_molformer/finetune/finetune_pubchem_light.py
gt4sd_molformer/finetune/finetune_pubchem_light_classification.py
gt4sd_molformer/finetune/finetune_pubchem_light_classification_multitask.py
gt4sd_molformer/finetune/ft_args.py
gt4sd_molformer/finetune/ft_utils.py
gt4sd_molformer/finetune/ft_rotate_attention/__init__.py
gt4sd_molformer/finetune/ft_rotate_attention/ft_attention_layer.py
gt4sd_molformer/finetune/ft_rotate_attention/ft_rotary.py
gt4sd_molformer/finetune/ft_rotate_attention/ft_rotate_builder.py
gt4sd_molformer/finetune/ft_tokenizer/__init__.py
gt4sd_molformer/finetune/ft_tokenizer/ft_tokenizer.py
gt4sd_molformer/training/__init__.py
gt4sd_molformer/training/args.py
gt4sd_molformer/training/bert_vocab.txt
gt4sd_molformer/training/dataset_pubchem.py
gt4sd_molformer/training/pubchem_canon_script.py
gt4sd_molformer/training/pubchem_canon_zinc_final_vocab_sorted.pth
gt4sd_molformer/training/pubchem_encoder.py
gt4sd_molformer/training/pubchem_script.py
gt4sd_molformer/training/train_pubchem_light.py
gt4sd_molformer/training/utils.py
gt4sd_molformer/training/val_script.py
gt4sd_molformer/training/zinc_script.py
gt4sd_molformer/training/rotate_attention/__init__.py
gt4sd_molformer/training/rotate_attention/attention_layer.py
gt4sd_molformer/training/rotate_attention/rotary.py
gt4sd_molformer/training/rotate_attention/rotate_builder.py
gt4sd_molformer/training/tokenizer/__init__.py
gt4sd_molformer/training/tokenizer/tokenizer.py
gt4sd_molformer-0.1.3.dist-info/LICENSE
gt4sd_molformer-0.1.3.dist-info/METADATA
gt4sd_molformer-0.1.3.dist-info/WHEEL
gt4sd_molformer-0.1.3.dist-info/top_level.txt
gt4sd_molformer-0.1.3.dist-info/RECORD
