Metadata-Version: 2.1
Name: gt4sd-molformer
Version: 0.1.3
Summary: Molformer's submodule of GT4SD.
Author: GT4SD team
Classifier: Operating System :: OS Independent
Classifier: Programming Language :: Python :: 3
Classifier: Programming Language :: Python :: 3.7
Classifier: Programming Language :: Python :: 3.8
License-File: LICENSE
Requires-Dist: datasets (>=1.11.0)
Requires-Dist: debugpy (>=1.6.6)
Requires-Dist: importlib-resources (>=5.10.0)
Requires-Dist: pandas (>=1.3.5)
Requires-Dist: torch (<=1.12.1,>=1.0)
Requires-Dist: pytorch-lightning (<=1.7.7)
Requires-Dist: pytorch-fast-transformers (>=0.4.0)
Requires-Dist: rdkit-pypi (<=2021.9.4,>=2020.9.5.2)
Requires-Dist: scikit-learn (>=1.0.0)
Requires-Dist: transformers (<4.26.0)
Requires-Dist: wheel (>=0.26)
